flask_validator/__init__.py
flask_validator/exceptions.py
flask_validator/validator.py
flask_validator/constraints/__init__.py
flask_validator/constraints/comparison.py
flask_validator/constraints/financial.py
flask_validator/constraints/internet.py
flask_validator/constraints/location.py
flask_validator/constraints/numbers.py
flask_validator/constraints/others.py
flask_validator/constraints/types.py
Flask_Validator-1.4.dist-info/LICENSE
Flask_Validator-1.4.dist-info/METADATA
Flask_Validator-1.4.dist-info/WHEEL
Flask_Validator-1.4.dist-info/top_level.txt
Flask_Validator-1.4.dist-info/RECORD
