Metadata-Version: 1.1
Name: Flask-Validator
Version: 1.4
Summary: Data validator for Flask and SQL-Alchemy, working at Model component with events
Home-page: https://github.com/xeBuz/Flask-Validator
Author: Jesus Roldan
Author-email: jesus.roldan@gmail.com
License: Mozilla Public License
Platform: any
Classifier: Development Status :: 5 - Production/Stable
Classifier: Environment :: Plugins
Classifier: Framework :: Flask
Classifier: Intended Audience :: Developers
Classifier: License :: OSI Approved :: Mozilla Public License 2.0 (MPL 2.0)
Classifier: Operating System :: OS Independent
Classifier: Programming Language :: Python
Classifier: Programming Language :: Python :: 2.7
Classifier: Programming Language :: Python :: 3.4
Classifier: Programming Language :: Python :: 3.5
Classifier: Programming Language :: Python :: 3.6
Classifier: Programming Language :: Python :: 3.7
Classifier: Topic :: Database
Classifier: Topic :: Software Development :: Libraries :: Python Modules
